MANIFEST.in
README.rst
setup.py
wrapper.sh
jobbergate/__init__.py
jobbergate/appform.py
jobbergate/cli.py
jobbergate/config.py
jobbergate/lib.py
jobbergate/models.py
jobbergate/views.py
jobbergate/workflow.py
jobbergate.egg-info/PKG-INFO
jobbergate.egg-info/SOURCES.txt
jobbergate.egg-info/dependency_links.txt
jobbergate.egg-info/not-zip-safe
jobbergate.egg-info/requires.txt
jobbergate.egg-info/top_level.txt
jobbergate/static/main.css
jobbergate/static/main.js
jobbergate/templates/_base.html
jobbergate/templates/footer.html
jobbergate/templates/header.html
jobbergate/templates/wtf.html
jobbergate/templates/errors/401.html
jobbergate/templates/errors/403.html
jobbergate/templates/errors/404.html
jobbergate/templates/errors/500.html
jobbergate/templates/main/about.html
jobbergate/templates/main/form.html
jobbergate/templates/main/home.html