Metadata-Version: 2.1
Name: jobbergate
Version: 1.2.0
Summary: Questionnaire application that populates Jinja2 templates with given answers.
Home-page: https://github.com/HeMan/jobbergate
Author: Jimmy Hedman
Author-email: jimmy.hedman@cygni.se
License: UNKNOWN
Platform: UNKNOWN
Classifier: Development Status :: 5 - Production/Stable
Classifier: Programming Language :: Python :: 3
Classifier: Programming Language :: Python :: 3.6
Classifier: Programming Language :: Python :: 3.7
Classifier: Programming Language :: Python :: 3.8
